{"id": "gen9vgc2025regibo3-2353920317", "format": "[Gen 9] VGC 2025 Reg I (Bo3)", "players": ["Squ1dge_", "Ashleemaster"], "log": "|j|\u2606Squ1dge_\n|j|\u2606Ashleemaster\n|html|<table width=\"100%\"><tr><td align=\"left\">Squ1dge_</td><td align=\"right\">Ashleemaster</tr><tr><td align=\"left\"><i class=\"fa fa-circle\"></i> <i class=\"fa fa-circle-o\"></i> </td><td align=\"right\"><i class=\"fa fa-circle-o\"></i> <i class=\"fa fa-circle\"></i> </tr></table>\n|uhtml|bestof|<h2><strong>Game 3</strong> of <a href=\"/game-bestof3-gen9vgc2025regibo3-2353916035\">a best-of-3</a></h2>\n|t:|1746018956\n|gametype|doubles\n|player|p1|Squ1dge_|1|\n|player|p2|Ashleemaster|oleana|\n|teamsize|p1|6\n|teamsize|p2|6\n|gen|9\n|tier|[Gen 9] VGC 2025 Reg I (Bo3)\n|rule|Species Clause: Limit one of each Pok\u00e9mon\n|rule|Item Clause: Limit 1 of each item\n|clearpoke\n|poke|p1|Zamazenta-*, L50|\n|poke|p1|Calyrex-Shadow, L50|\n|poke|p1|Tornadus, L50, M|\n|poke|p1|Urshifu-*, L50, M|\n|poke|p1|Amoonguss, L50, M|\n|poke|p1|Chien-Pao, L50|\n|poke|p2|Zacian-*, L50|\n|poke|p2|Lunala, L50|\n|poke|p2|Tornadus, L50, M|\n|poke|p2|Urshifu-*, L50, M|\n|poke|p2|Ogerpon-Hearthflame, L50, F|\n|poke|p2|Indeedee-F, L50, F|\n|teampreview|4\n|showteam|p1|Zamazenta-Crowned||RustedShield|DauntlessShield|BodyPress,HeavySlam,WideGuard,Protect||||||50|,,,,,Dragon]Calyrex-Shadow||LifeOrb|AsOneSpectrier|AstralBarrage,Psychic,NastyPlot,Protect||||||50|,,,,,Dark]Tornadus||CovertCloak|Prankster|BleakwindStorm,Tailwind,RainDance,Taunt|||M|||50|,,,,,Dark]Urshifu-Rapid-Strike||MysticWater|UnseenFist|SurgingStrikes,CloseCombat,AquaJet,Detect|||M|||50|,,,,,Water]Amoonguss||RockyHelmet|Regenerator|SludgeBomb,Spore,RagePowder,Protect|||M|||50|,,,,,Water]Chien-Pao||FocusSash|SwordofRuin|SuckerPunch,Crunch,IceSpinner,Protect||||||50|,,,,,Stellar\n|showteam|p2|Zacian-Crowned||RustedSword|IntrepidSword|behemothblade,PlayRough,SacredSword,Protect||||||50|,,,,,Fairy]Lunala||PowerHerb|ShadowShield|WideGuard,ExpandingForce,MoongeistBeam,MeteorBeam||||||50|,,,,,Fairy]Tornadus||CovertCloak|Prankster|BleakwindStorm,Taunt,Tailwind,RainDance|||M|||50|,,,,,Dark]Urshifu-Rapid-Strike||MysticWater|UnseenFist|SurgingStrikes,CloseCombat,AquaJet,Detect|||M|||50|,,,,,Water]Ogerpon-Hearthflame||HearthflameMask|MoldBreaker|IvyCudgel,WoodHammer,SpikyShield,FollowMe|||F|||50|,,,,,Fire]Indeedee-F||PsychicSeed|PsychicSurge|LightScreen,FollowMe,HealPulse,TrickRoom|||F|||50|,,,,,Grass\n|inactive|Battle timer is ON: inactive players will automatically lose when time's up. (requested by Ashleemaster)\n|inactive|Ashleemaster has 60 seconds left.\n|\n|t:|1746018989\n|start\n|switch|p1a: Zamazenta|Zamazenta-Crowned, L50|100/100\n|switch|p1b: Chien-Pao|Chien-Pao, L50|100/100\n|switch|p2a: Urshifu|Urshifu-Rapid-Strike, L50, M|100/100\n|switch|p2b: Lunala|Lunala, L50|100/100\n|-ability|p1b: Chien-Pao|Sword of Ruin\n|-ability|p1a: Zamazenta|Dauntless Shield|boost\n|-boost|p1a: Zamazenta|def|1\n|turn|1\n|\n|t:|1746019005\n|switch|p2b: Indeedee|Indeedee-F, L50, F|100/100\n|-fieldstart|move: Psychic Terrain|[from] ability: Psychic Surge|[of] p2b: Indeedee\n|-enditem|p2b: Indeedee|Psychic Seed\n|-boost|p2b: Indeedee|spd|1|[from] item: Psychic Seed\n|move|p1b: Chien-Pao|Crunch|p2b: Indeedee\n|-supereffective|p2b: Indeedee\n|-damage|p2b: Indeedee|0 fnt\n|faint|p2b: Indeedee\n|move|p1a: Zamazenta|Body Press|p2a: Urshifu\n|-damage|p2a: Urshifu|13/100\n|move|p2a: Urshifu|Surging Strikes|p1b: Chien-Pao\n|-crit|p1b: Chien-Pao\n|-damage|p1b: Chien-Pao|65/100\n|-crit|p1b: Chien-Pao\n|-damage|p1b: Chien-Pao|30/100\n|-crit|p1b: Chien-Pao\n|-damage|p1b: Chien-Pao|0 fnt\n|faint|p1b: Chien-Pao\n|-hitcount|p1: Chien-Pao|3\n|\n|upkeep\n|\n|t:|1746019020\n|switch|p1b: Calyrex|Calyrex-Shadow, L50|100/100\n|switch|p2b: Lunala|Lunala, L50|100/100\n|-ability|p1b: Calyrex|As One\n|-ability|p1b: Calyrex|Unnerve\n|turn|2\n|\n|t:|1746019032\n|-terastallize|p1b: Calyrex|Dark\n|-terastallize|p2b: Lunala|Fairy\n|move|p2a: Urshifu|Detect|p2a: Urshifu\n|-singleturn|p2a: Urshifu|Protect\n|move|p1b: Calyrex|Psychic|p2a: Urshifu\n|-activate|p2a: Urshifu|move: Protect\n|move|p1a: Zamazenta|Heavy Slam|p2b: Lunala\n|-supereffective|p2b: Lunala\n|-damage|p2b: Lunala|66/100\n|move|p2b: Lunala|Expanding Force|p1b: Calyrex|[spread] p1a\n|-immune|p1b: Calyrex\n|-damage|p1a: Zamazenta|47/100\n|\n|upkeep\n|turn|3\n|\n|t:|1746019054\n|move|p1b: Calyrex|Psychic|p2a: Urshifu\n|-supereffective|p2a: Urshifu\n|-damage|p2a: Urshifu|0 fnt\n|faint|p2a: Urshifu\n|-ability|p1b: Calyrex|Grim Neigh|boost\n|-boost|p1b: Calyrex|spa|1\n|-damage|p1b: Calyrex|91/100|[from] item: Life Orb\n|move|p1a: Zamazenta|Heavy Slam|p2b: Lunala\n|-supereffective|p2b: Lunala\n|-damage|p2b: Lunala|0 fnt\n|faint|p2b: Lunala\n|\n|upkeep\n|\n|t:|1746019063\n|switch|p2b: Zacian|Zacian-Crowned, L50|100/100\n|-ability|p2b: Zacian|Intrepid Sword|boost\n|-boost|p2b: Zacian|atk|1\n|turn|4\n|\n|t:|1746019070\n|switch|p1a: Amoonguss|Amoonguss, L50, M|100/100\n|move|p1b: Calyrex|Protect|p1b: Calyrex\n|-singleturn|p1b: Calyrex|Protect\n|move|p2b: Zacian|Play Rough|p1b: Calyrex\n|-activate|p1b: Calyrex|move: Protect\n|\n|upkeep\n|turn|5\n|\n|t:|1746019077\n|move|p1a: Amoonguss|Rage Powder|p1a: Amoonguss\n|-singleturn|p1a: Amoonguss|move: Rage Powder\n|move|p1b: Calyrex|Astral Barrage|p2b: Zacian\n|-damage|p2b: Zacian|0 fnt\n|faint|p2b: Zacian\n|-damage|p1b: Calyrex|81/100|[from] item: Life Orb\n|\n|win|Squ1dge_\n", "uploadtime": 1746019104, "views": 23, "formatid": "gen9vgc2025regibo3", "rating": null, "private": 0, "password": null}