{"id": "gen9vgc2025regibo3-2354033978", "format": "[Gen 9] VGC 2025 Reg I (Bo3)", "players": ["practicesemijrlman", "craloo"], "log": "|j|\u2606practicesemijrlman\n|j|\u2606craloo\n|html|<table width=\"100%\"><tr><td align=\"left\">practicesemijrlman</td><td align=\"right\">craloo</tr><tr><td align=\"left\"><i class=\"fa fa-circle\"></i> <i class=\"fa fa-circle-o\"></i> </td><td align=\"right\"><i class=\"fa fa-circle-o\"></i> <i class=\"fa fa-circle\"></i> </tr></table>\n|uhtml|bestof|<h2><strong>Game 3</strong> of <a href=\"/game-bestof3-gen9vgc2025regibo3-2354028760\">a best-of-3</a></h2>\n|t:|1746029229\n|gametype|doubles\n|player|p1|practicesemijrlman|lucas|1322\n|player|p2|craloo|marlon|1377\n|teamsize|p1|6\n|teamsize|p2|6\n|gen|9\n|tier|[Gen 9] VGC 2025 Reg I (Bo3)\n|rated|\n|rule|Species Clause: Limit one of each Pok\u00e9mon\n|rule|Item Clause: Limit 1 of each item\n|clearpoke\n|poke|p1|Zacian-*, L50|\n|poke|p1|Chien-Pao, L50|\n|poke|p1|Kyogre, L50|\n|poke|p1|Tornadus, L50, M|\n|poke|p1|Iron Bundle, L50|\n|poke|p1|Raichu, L50, F|\n|poke|p2|Kyogre, L50|\n|poke|p2|Zacian-*, L50|\n|poke|p2|Rillaboom, L50, F|\n|poke|p2|Incineroar, L50, M|\n|poke|p2|Tornadus, L50, M|\n|poke|p2|Urshifu-*, L50, F|\n|teampreview|4\n|showteam|p1|Zacian-Crowned||RustedSword|IntrepidSword|behemothblade,PlayRough,SacredSword,Protect||||||50|,,,,,Fire]Chien-Pao||FocusSash|SwordofRuin|SuckerPunch,IceSpinner,SacredSword,Protect||||||50|,,,,,Ghost]Kyogre||ChoiceSpecs|Drizzle|WaterSpout,HydroPump,OriginPulse,IceBeam||||||50|,,,,,Water]Tornadus||CovertCloak|Prankster|BleakwindStorm,Taunt,RainDance,Tailwind|||M|||50|,,,,,Steel]Iron Bundle||BoosterEnergy|QuarkDrive|Encore,IcyWind,FreezeDry,Protect||||||50|,,,,,Ghost]Raichu||AssaultVest|LightningRod|Electroweb,FakeOut,Nuzzle,Feint|||F|||50|,,,,,Water\n|showteam|p2|Kyogre||Leftovers|Drizzle|WaterSpout,OriginPulse,IceBeam,Protect||||||50|,,,,,Grass]Zacian-Crowned||RustedSword|IntrepidSword|behemothblade,PlayRough,SacredSword,Protect||||||50|,,,,,Stellar]Rillaboom||AssaultVest|GrassySurge|WoodHammer,GrassyGlide,Uturn,FakeOut|||F|||50|,,,,,Fire]Incineroar||RockyHelmet|Intimidate|KnockOff,Taunt,PartingShot,FakeOut|||M|||50|,,,,,Ghost]Tornadus||CovertCloak|Prankster|BleakwindStorm,RainDance,Tailwind,Protect|||M|||50|,,,,,Dark]Urshifu||FocusSash|UnseenFist|WickedBlow,SuckerPunch,CloseCombat,Detect|||F|||50|,,,,,Stellar\n|inactive|Battle timer is ON: inactive players will automatically lose when time's up. (requested by practicesemijrlman)\n|inactive|practicesemijrlman has 60 seconds left.\n|inactive|craloo has 60 seconds left.\n|\n|t:|1746029262\n|start\n|switch|p1a: Tornadus|Tornadus, L50, M|100/100\n|switch|p1b: Zacian|Zacian-Crowned, L50|100/100\n|switch|p2a: Zacian|Zacian-Crowned, L50|100/100\n|switch|p2b: Rillaboom|Rillaboom, L50, F|100/100\n|-ability|p1b: Zacian|Intrepid Sword|boost\n|-boost|p1b: Zacian|atk|1\n|-ability|p2a: Zacian|Intrepid Sword|boost\n|-boost|p2a: Zacian|atk|1\n|-fieldstart|move: Grassy Terrain|[from] ability: Grassy Surge|[of] p2b: Rillaboom\n|turn|1\n|\n|t:|1746029280\n|move|p1b: Zacian|Protect|p1b: Zacian\n|-singleturn|p1b: Zacian|Protect\n|move|p1a: Tornadus|Tailwind|p1a: Tornadus\n|-sidestart|p1: practicesemijrlman|move: Tailwind\n|move|p2a: Zacian|Behemoth Blade|p1a: Tornadus\n|-damage|p1a: Tornadus|0 fnt\n|faint|p1a: Tornadus\n|move|p2b: Rillaboom|U-turn|p1b: Zacian\n|-activate|p1b: Zacian|move: Protect\n|\n|upkeep\n|\n|t:|1746029295\n|switch|p1a: Chien-Pao|Chien-Pao, L50|100/100\n|-ability|p1a: Chien-Pao|Sword of Ruin\n|turn|2\n|\n|t:|1746029315\n|-terastallize|p1b: Zacian|Fire\n|-terastallize|p2b: Rillaboom|Fire\n|move|p2a: Zacian|Protect|p2a: Zacian\n|-singleturn|p2a: Zacian|Protect\n|move|p1b: Zacian|Behemoth Blade|p2a: Zacian\n|-activate|p2a: Zacian|move: Protect\n|move|p1a: Chien-Pao|Ice Spinner|p2b: Rillaboom\n|-resisted|p2b: Rillaboom\n|-damage|p2b: Rillaboom|78/100\n|-fieldend|move: Grassy Terrain\n|move|p2b: Rillaboom|U-turn|p1a: Chien-Pao\n|-supereffective|p1a: Chien-Pao\n|-damage|p1a: Chien-Pao|36/100\n|\n|t:|1746029330\n|switch|p2b: Kyogre|Kyogre, L50|100/100|[from] U-turn\n|-weather|RainDance|[from] ability: Drizzle|[of] p2b: Kyogre\n|\n|-weather|RainDance|[upkeep]\n|upkeep\n|turn|3\n|\n|t:|1746029344\n|move|p1a: Chien-Pao|Sucker Punch|p2b: Kyogre\n|-damage|p2b: Kyogre|53/100\n|move|p1b: Zacian|Behemoth Blade|p2a: Zacian\n|-damage|p2a: Zacian|0 fnt\n|faint|p2a: Zacian\n|move|p2b: Kyogre|Origin Pulse|p1a: Chien-Pao|[spread] p1a,p1b\n|-supereffective|p1b: Zacian\n|-damage|p1a: Chien-Pao|0 fnt\n|-damage|p1b: Zacian|0 fnt\n|faint|p1a: Chien-Pao\n|faint|p1b: Zacian\n|\n|-weather|RainDance|[upkeep]\n|-heal|p2b: Kyogre|59/100|[from] item: Leftovers\n|upkeep\n|\n|t:|1746029350\n|switch|p1b: Kyogre|Kyogre, L50|100/100\n|switch|p2a: Tornadus|Tornadus, L50, M, shiny|100/100\n|turn|4\n|c|\u2606craloo|wp\n|\n|t:|1746029356\n|move|p2b: Kyogre|Protect|p2b: Kyogre\n|-singleturn|p2b: Kyogre|Protect\n|move|p2a: Tornadus|Tailwind|p2a: Tornadus\n|-sidestart|p2: craloo|move: Tailwind\n|move|p1b: Kyogre|Water Spout|p2b: Kyogre|[spread] p2a\n|-activate|p2b: Kyogre|move: Protect\n|-damage|p2a: Tornadus|0 fnt\n|faint|p2a: Tornadus\n|\n|-weather|RainDance|[upkeep]\n|-heal|p2b: Kyogre|66/100|[from] item: Leftovers\n|-sideend|p1: practicesemijrlman|move: Tailwind\n|upkeep\n|\n|t:|1746029357\n|switch|p2a: Rillaboom|Rillaboom, L50, F, tera:Fire|78/100\n|-fieldstart|move: Grassy Terrain|[from] ability: Grassy Surge|[of] p2a: Rillaboom\n|turn|5\n|c|\u2606practicesemijrlman|ggwp\n|\n|t:|1746029364\n|move|p2a: Rillaboom|Wood Hammer|p1b: Kyogre\n|-supereffective|p1b: Kyogre\n|-crit|p1b: Kyogre\n|-damage|p1b: Kyogre|0 fnt\n|faint|p1b: Kyogre\n|-damage|p2a: Rillaboom|50/100|[from] Recoil\n|\n|win|craloo\n|raw|practicesemijrlman's rating: 1322 &rarr; <strong>1305</strong><br />(-17 for losing)\n|raw|craloo's rating: 1377 &rarr; <strong>1394</strong><br />(+17 for winning)\n|l|\u2606craloo\n|player|p2|\n|l|\u2606practicesemijrlman\n|player|p1|\n", "uploadtime": 1746029401, "views": 22, "formatid": "gen9vgc2025regibo3", "rating": 1305, "private": 0, "password": null}