{"id": "gen9vgc2025regibo3-2353921717", "format": "[Gen 9] VGC 2025 Reg I (Bo3)", "players": ["Mona Aster", "Arnauz10"], "log": "|j|\u2606Mona Aster\n|j|\u2606Arnauz10\n|html|<table width=\"100%\"><tr><td align=\"left\">Mona Aster</td><td align=\"right\">Arnauz10</tr><tr><td align=\"left\"><i class=\"fa fa-circle-o\"></i> <i class=\"fa fa-circle-o\"></i> </td><td align=\"right\"><i class=\"fa fa-circle-o\"></i> <i class=\"fa fa-circle-o\"></i> </tr></table>\n|uhtml|bestof|<h2><strong>Game 1</strong> of <a href=\"/game-bestof3-gen9vgc2025regibo3-2353921716\">a best-of-3</a></h2>\n|t:|1746019098\n|gametype|doubles\n|player|p1|Mona Aster|266|1141\n|player|p2|Arnauz10|hilbert|1054\n|teamsize|p1|6\n|teamsize|p2|6\n|gen|9\n|tier|[Gen 9] VGC 2025 Reg I (Bo3)\n|rated|\n|rule|Species Clause: Limit one of each Pok\u00e9mon\n|rule|Item Clause: Limit 1 of each item\n|clearpoke\n|poke|p1|Lunala, L50|\n|poke|p1|Groudon, L50|\n|poke|p1|Incineroar, L50, M|\n|poke|p1|Flutter Mane, L50|\n|poke|p1|Urshifu-*, L50, F|\n|poke|p1|Raging Bolt, L50|\n|poke|p2|Terapagos, L50, M|\n|poke|p2|Incineroar, L50, M|\n|poke|p2|Rillaboom, L50, M|\n|poke|p2|Landorus, L50, M|\n|poke|p2|Ogerpon-Hearthflame, L50, F|\n|poke|p2|Calyrex-Shadow, L50|\n|teampreview|4\n|showteam|p1|Lunala||PowerHerb|ShadowShield|TrickRoom,MeteorBeam,WideGuard,MoongeistBeam||||||50|,,,,,Water]Groudon||ClearAmulet|Drought|Protect,PrecipiceBlades,HeatCrash,Substitute||||||50|,,,,,Fire]Incineroar||SafetyGoggles|Intimidate|FlareBlitz,KnockOff,FakeOut,PartingShot|||M|||50|,,,,,Ghost]Flutter Mane||FocusSash|Protosynthesis|Moonblast,Taunt,IcyWind,Protect||||||50|,,,,,Grass]Urshifu||ChoiceScarf|UnseenFist|WickedBlow,CloseCombat,Uturn,PoisonJab|||F|||50|,,,,,Stellar]Raging Bolt||AssaultVest|Protosynthesis|Electroweb,Thunderclap,Snarl,DracoMeteor||||||50|,,,,,Electric\n|showteam|p2|Terapagos||Leftovers|TeraShift|TeraStarstorm,Protect,CalmMind,EarthPower|||M|||50|,,,,,Stellar]Incineroar||RockyHelmet|Intimidate|KnockOff,FakeOut,PartingShot,WillOWisp|||M|||50|,,,,,Poison]Rillaboom||AssaultVest|GrassySurge|GrassyGlide,WoodHammer,FakeOut,Uturn|||M|||50|,,,,,Grass]Landorus||ChoiceScarf|SheerForce|EarthPower,SludgeBomb,Psychic,SandsearStorm|||M|||50|,,,,,Ghost]Ogerpon-Hearthflame||HearthflameMask|MoldBreaker|SpikyShield,IvyCudgel,FollowMe,GrassyGlide|||F|||50|,,,,,Fire]Calyrex-Shadow||FocusSash|AsOneSpectrier|Protect,Encore,Disable,AstralBarrage||||||50|,,,,,Ghost\n|\n|t:|1746019199\n|start\n|switch|p1a: Lunala|Lunala, L50|100/100\n|switch|p1b: Flutter Mane|Flutter Mane, L50|100/100\n|switch|p2a: Ogerpon|Ogerpon-Hearthflame, L50, F|100/100\n|switch|p2b: Calyrex|Calyrex-Shadow, L50|100/100\n|-ability|p2b: Calyrex|As One\n|-ability|p2b: Calyrex|Unnerve\n|-ability|p2a: Ogerpon|Mold Breaker\n|turn|1\n|\n|t:|1746019242\n|move|p2b: Calyrex|Protect|p2b: Calyrex\n|-singleturn|p2b: Calyrex|Protect\n|move|p1a: Lunala|Wide Guard|p1a: Lunala\n|-singleturn|p1a: Lunala|Wide Guard\n|move|p1b: Flutter Mane|Taunt|p2b: Calyrex\n|-activate|p2b: Calyrex|move: Protect\n|move|p2a: Ogerpon|Ivy Cudgel|p1b: Flutter Mane|[anim] Ivy Cudgel Fire\n|-enditem|p1b: Flutter Mane|Focus Sash\n|-damage|p1b: Flutter Mane|1/100\n|\n|upkeep\n|turn|2\n|\n|t:|1746019307\n|-terastallize|p2a: Ogerpon|Fire\n|detailschange|p2a: Ogerpon|Ogerpon-Hearthflame-Tera, L50, F, tera:Fire\n|-ability|p2a: Ogerpon|Embody Aspect (Hearthflame)|boost\n|-boost|p2a: Ogerpon|atk|1\n|move|p2b: Calyrex|Astral Barrage|p1b: Flutter Mane|[spread] p1a,p1b\n|-supereffective|p1a: Lunala\n|-supereffective|p1b: Flutter Mane\n|-damage|p1a: Lunala|25/100\n|-damage|p1b: Flutter Mane|0 fnt\n|faint|p1b: Flutter Mane\n|-end|p1b: Flutter Mane|Protosynthesis|[silent]\n|-ability|p2b: Calyrex|Grim Neigh|boost\n|-boost|p2b: Calyrex|spa|1\n|move|p2a: Ogerpon|Ivy Cudgel|p1a: Lunala|[anim] Ivy Cudgel Fire\n|-damage|p1a: Lunala|0 fnt\n|faint|p1a: Lunala\n|\n|upkeep\n|\n|t:|1746019329\n|switch|p1b: Groudon|Groudon, L50|100/100\n|switch|p1a: Urshifu|Urshifu, L50, F|100/100\n|-weather|SunnyDay|[from] ability: Drought|[of] p1b: Groudon\n|turn|3\n|\n|t:|1746019359\n|move|p2b: Calyrex|Protect|p2b: Calyrex\n|-singleturn|p2b: Calyrex|Protect\n|move|p1a: Urshifu|Wicked Blow|p2b: Calyrex\n|-supereffective|p2b: Calyrex\n|-crit|p2b: Calyrex\n|-enditem|p2b: Calyrex|Focus Sash\n|-damage|p2b: Calyrex|1/100\n|move|p2a: Ogerpon|Ivy Cudgel|p1a: Urshifu|[anim] Ivy Cudgel Fire\n|-damage|p1a: Urshifu|0 fnt\n|faint|p1a: Urshifu\n|move|p1b: Groudon|Precipice Blades|p2a: Ogerpon|[spread] p2a\n|-activate|p2b: Calyrex|move: Protect\n|-supereffective|p2a: Ogerpon\n|-damage|p2a: Ogerpon|0 fnt\n|faint|p2a: Ogerpon\n|\n|-weather|SunnyDay|[upkeep]\n|upkeep\n|l|\u2606Mona Aster\n|player|p1|\n|j|\u2606Mona Aster\n|player|p1|Mona Aster|266|\n|\n|t:|1746019372\n|switch|p2a: Landorus|Landorus, L50, M|100/100\n|turn|4\n|\n|t:|1746019397\n|move|p1b: Groudon|Protect|p1b: Groudon\n|-singleturn|p1b: Groudon|Protect\n|move|p2a: Landorus|Earth Power|p1b: Groudon\n|-activate|p1b: Groudon|move: Protect\n|move|p2b: Calyrex|Encore|p1b: Groudon\n|-activate|p1b: Groudon|move: Protect\n|\n|-weather|SunnyDay|[upkeep]\n|upkeep\n|turn|5\n|-message|Mona Aster forfeited.\n|\n|win|Arnauz10\n", "uploadtime": 1746019416, "views": 18, "formatid": "gen9vgc2025regibo3", "rating": null, "private": 0, "password": null}