{"id": "gen9vgc2025regibo3-2353350761", "format": "[Gen 9] VGC 2025 Reg I (Bo3)", "players": ["rrrrugo", "G00bermeister69420"], "log": "|j|\u2606rrrrugo\n|j|\u2606G00bermeister69420\n|html|<table width=\"100%\"><tr><td align=\"left\">rrrrugo</td><td align=\"right\">G00bermeister69420</tr><tr><td align=\"left\"><i class=\"fa fa-circle-o\"></i> <i class=\"fa fa-circle-o\"></i> </td><td align=\"right\"><i class=\"fa fa-circle-o\"></i> <i class=\"fa fa-circle-o\"></i> </tr></table>\n|uhtml|bestof|<h2><strong>Game 1</strong> of <a href=\"/game-bestof3-gen9vgc2025regibo3-2353350760\">a best-of-3</a></h2>\n|t:|1745948565\n|gametype|doubles\n|player|p1|rrrrugo|102|1000\n|player|p2|G00bermeister69420|hiker-gen4|1032\n|teamsize|p1|6\n|teamsize|p2|6\n|gen|9\n|tier|[Gen 9] VGC 2025 Reg I (Bo3)\n|rated|\n|rule|Species Clause: Limit one of each Pok\u00e9mon\n|rule|Item Clause: Limit 1 of each item\n|clearpoke\n|poke|p1|Lunala, L50|\n|poke|p1|Indeedee-F, L50, F|\n|poke|p1|Incineroar, L50, M|\n|poke|p1|Ogerpon-Hearthflame, L50, F|\n|poke|p1|Koraidon, L50|\n|poke|p1|Raging Bolt, L50|\n|poke|p2|Regidrago, L50|\n|poke|p2|Zacian-*, L50|\n|poke|p2|Calyrex-Ice, L50|\n|poke|p2|Ogerpon-Cornerstone, L50, F|\n|poke|p2|Chandelure, L50, F|\n|poke|p2|Ursaluna, L50, M|\n|teampreview|4\n|showteam|p1|Lunala||PowerHerb|ShadowShield|MoongeistBeam,MeteorBeam,ExpandingForce,WideGuard||||||50|,,,,,Water]Indeedee-F||PsychicSeed|PsychicSurge|FollowMe,TrickRoom,HelpingHand,DazzlingGleam|||F|||50|,,,,,Fairy]Incineroar||SafetyGoggles|Intimidate|KnockOff,WillOWisp,PartingShot,FakeOut|||M|||50|,,,,,Ghost]Ogerpon-Hearthflame||HearthflameMask|MoldBreaker|IvyCudgel,HornLeech,SpikyShield,FocusEnergy|||F|||50|,,,,,Fire]Koraidon||ClearAmulet|OrichalcumPulse|FlareBlitz,Protect,CollisionCourse,FlameCharge||||||50|,,,,,Fire]Raging Bolt||AssaultVest|Protosynthesis|Thunderbolt,Thunderclap,DracoMeteor,Electroweb||||||50|,,,,,Fairy\n|showteam|p2|Regidrago||IronBall|DragonsMaw|DragonEnergy,EarthPower,BreakingSwipe,Protect||||||50|,,,,,Dragon]Zacian-Crowned||RustedSword|IntrepidSword|behemothblade,PlayRough,SacredSword,Protect||||||50|,,,,,Fighting]Calyrex-Ice||PowerLens|AsOneGlastrier|GlacialLance,HealPulse,CloseCombat,TrickRoom||||||50|,,,,,Water]Ogerpon-Cornerstone||CornerstoneMask|Sturdy|SpikyShield,Taunt,FollowMe,IvyCudgel|||F|||50|,,,,,Rock]Chandelure||FocusSash|Infiltrator|TrickRoom,Flamethrower,ShadowBall,DarkPulse|||F|||50|,,,,,Ghost]Ursaluna||FlameOrb|Guts|Facade,ThroatChop,Protect,HeadlongRush|||M|||50|,,,,,Fighting\n|inactive|Battle timer is ON: inactive players will automatically lose when time's up. (requested by rrrrugo)\n|\n|t:|1745948598\n|start\n|switch|p1a: Koraidon|Koraidon, L50|100/100\n|switch|p1b: Incineroar|Incineroar, L50, M, shiny|100/100\n|switch|p2a: Timmy|Ogerpon-Cornerstone, L50, F|100/100\n|switch|p2b: Chandelure|Chandelure, L50, F|100/100\n|-weather|SunnyDay|[from] ability: Orichalcum Pulse|[of] p1a: Koraidon\n|-activate|p1a: Koraidon|Orichalcum Pulse|[source]\n|-ability|p1b: Incineroar|Intimidate|boost\n|-unboost|p2a: Timmy|atk|1\n|-unboost|p2b: Chandelure|atk|1\n|turn|1\n|inactive|rrrrugo has 30 seconds left.\n|\n|t:|1745948626\n|move|p1b: Incineroar|Fake Out|p2a: Timmy\n|-resisted|p2a: Timmy\n|-damage|p2a: Timmy|93/100\n|cant|p2a: Timmy|flinch\n|move|p1a: Koraidon|Flame Charge|p2b: Chandelure\n|-resisted|p2b: Chandelure\n|-damage|p2b: Chandelure|79/100\n|-boost|p1a: Koraidon|spe|1\n|move|p2b: Chandelure|Trick Room|p2b: Chandelure\n|-fieldstart|move: Trick Room|[of] p2b: Chandelure\n|\n|-weather|SunnyDay|[upkeep]\n|upkeep\n|turn|2\n|\n|t:|1745948649\n|move|p2a: Timmy|Follow Me|p2a: Timmy\n|-singleturn|p2a: Timmy|move: Follow Me\n|move|p1b: Incineroar|Knock Off|p2a: Timmy\n|-damage|p2a: Timmy|60/100\n|move|p2b: Chandelure|Shadow Ball|p1a: Koraidon\n|-damage|p1a: Koraidon|52/100\n|move|p1a: Koraidon|Collision Course|p2a: Timmy\n|-supereffective|p2a: Timmy\n|-damage|p2a: Timmy|0 fnt\n|faint|p2a: Timmy\n|\n|-weather|SunnyDay|[upkeep]\n|upkeep\n|\n|t:|1745948665\n|switch|p2a: Ginshakaklook|Regidrago, L50|100/100\n|turn|3\n|\n|t:|1745948677\n|-terastallize|p2a: Ginshakaklook|Dragon\n|move|p1a: Koraidon|Protect|p1a: Koraidon\n|-singleturn|p1a: Koraidon|Protect\n|move|p2a: Ginshakaklook|Dragon Energy|p1b: Incineroar|[spread] p1b\n|-activate|p1a: Koraidon|move: Protect\n|-damage|p1b: Incineroar|11/100\n|move|p1b: Incineroar|Parting Shot|p2b: Chandelure\n|-unboost|p2b: Chandelure|atk|1\n|-unboost|p2b: Chandelure|spa|1\n|\n|t:|1745948692\n|switch|p1b: Ogerpon|Ogerpon-Hearthflame, L50, F|100/100|[from] Parting Shot\n|-ability|p1b: Ogerpon|Mold Breaker\n|move|p2b: Chandelure|Flamethrower|p1b: Ogerpon\n|-damage|p1b: Ogerpon|45/100\n|\n|-weather|SunnyDay|[upkeep]\n|upkeep\n|turn|4\n|inactive|rrrrugo has 30 seconds left.\n|\n|t:|1745948722\n|switch|p1a: Raging Bolt|Raging Bolt, L50|100/100\n|-activate|p1a: Raging Bolt|ability: Protosynthesis\n|-start|p1a: Raging Bolt|protosynthesisspa\n|-terastallize|p1b: Ogerpon|Fire\n|detailschange|p1b: Ogerpon|Ogerpon-Hearthflame-Tera, L50, F, tera:Fire\n|-ability|p1b: Ogerpon|Embody Aspect (Hearthflame)|boost\n|-boost|p1b: Ogerpon|atk|1\n|move|p2a: Ginshakaklook|Dragon Energy|p1a: Raging Bolt|[spread] p1a,p1b\n|-supereffective|p1a: Raging Bolt\n|-damage|p1a: Raging Bolt|0 fnt\n|-damage|p1b: Ogerpon|0 fnt\n|faint|p1a: Raging Bolt\n|-end|p1a: Raging Bolt|Protosynthesis|[silent]\n|faint|p1b: Ogerpon\n|move|p2b: Chandelure|Shadow Ball|p1: Raging Bolt|[notarget]\n|-fail|p2b: Chandelure\n|\n|-weather|SunnyDay|[upkeep]\n|upkeep\n|-message|rrrrugo forfeited.\n|raw|rrrrugo's rating: 1000 &rarr; <strong>1000</strong><br />(+0 for losing)\n|raw|G00bermeister69420's rating: 1032 &rarr; <strong>1064</strong><br />(+32 for winning)\n|\n|win|G00bermeister69420\n|l|\u2606rrrrugo\n|player|p1|\n", "uploadtime": 1745948743, "views": 12, "formatid": "gen9vgc2025regibo3", "rating": 1000, "private": 0, "password": null}